weight_analyse/__init__.py
weight_analyse/core.py
weight_analyse/log.py
weight_analyse/server.py
weight_analyse-0.1.1.dist-info/METADATA
weight_analyse-0.1.1.dist-info/WHEEL
weight_analyse-0.1.1.dist-info/top_level.txt
weight_analyse-0.1.1.dist-info/RECORD
